{
	"Ho_ten": "Triệu đình Hoa",
	"Ma_so": "HS_755",
	"CMND": "010255434",
	"Gioi_tinh": "Nữ",
	"Ngay_sinh": "2002-06-25T17:00:00.000Z",
	"Dia_chi": "23 Phùng đình Thúy,Phường 10,Quận Nhà bè, Ho Chi Minh City, Ho Chi Minh, Vietnam",
	"Lop": {
		"Ten": "Lớp 9.6",
		"Ma_so": "LOP_9.6",
		"Khoi": {
			"Ten": "Khối 9",
			"Ma_so": "KHOI_9"
		}
	},
	"Danh_sach_Vang": [
		{
			"Ngay": "2017-07-05T17:00:00.000Z",
			"Ly_do": ""
		},
		{
			"Ngay": "2017-07-12T17:00:00.000Z",
			"Ly_do": ""
		},
		{
			"Ngay": "2017-07-19T17:00:00.000Z",
			"Ly_do": ""
		}
	]
}